README.md
setup.py
EnteroTyper/__init__.py
EnteroTyper/enterotyper.py
EnteroTyper.egg-info/PKG-INFO
EnteroTyper.egg-info/SOURCES.txt
EnteroTyper.egg-info/dependency_links.txt
EnteroTyper.egg-info/entry_points.txt
EnteroTyper.egg-info/requires.txt
EnteroTyper.egg-info/top_level.txt
EnteroTyper/bin/__init__.py
EnteroTyper/bin/accessories.py
EnteroTyper/bin/bulk_typer.py
EnteroTyper/bin/compare_sequences_types.py
EnteroTyper/bin/concatenate_sequences.py
EnteroTyper/bin/typer.py
EnteroTyper/tests/__init__.py
EnteroTyper/tests/test_accessories.py
EnteroTyper/tests/test_bulk_typer.py
EnteroTyper/tests/test_compare_sequence_types.py
EnteroTyper/tests/test_concatenate_sequences.py
EnteroTyper/tests/test_typer.py