Metadata-Version: 2.1
Name: EnteroTyper
Version: 0.1.6
Summary: Scripts to type and compare assemblies based off of Enterobase schemes
Home-page: https://github.com/BFSSI-Bioinformatics-Lab/EnteroTyper
Author: Forest Dussault
Author-email: forest.dussault@canada.ca
License: UNKNOWN
Platform: UNKNOWN
Requires-Python: ~=3.6
